kodb/__init__.py
kodb/add_and_remove.py
kodb/build.py
kodb/download.py
kodb/edit_and_list.py
kodb/log.py
kodb/make_project.py
kodb/references.py
kodb/switch_and_move.py
kodb/utils.py
kodb-0.1.6.dist-info/LICENSE
kodb-0.1.6.dist-info/METADATA
kodb-0.1.6.dist-info/WHEEL
kodb-0.1.6.dist-info/entry_points.txt
kodb-0.1.6.dist-info/top_level.txt
kodb-0.1.6.dist-info/RECORD
