Metadata-Version: 2.1
Name: kodb
Version: 0.1.6
Summary: kmaasrud's opinionated document builder
Home-page: https://github.com/kmaasrud/kodb
Author: kmaasrud
Author-email: km@aasrud.com
License: UNKNOWN
Platform: UNKNOWN
Classifier: Programming Language :: Python :: 3
Classifier: License :: OSI Approved :: MIT License
Classifier: Operating System :: OS Independent
Requires-Python: >=3.6
Requires-Dist: pandoc-xnos
Requires-Dist: pandoc-fignos
Requires-Dist: pandoc-eqnos
Requires-Dist: pandoc-tablenos
Requires-Dist: pandoc-secnos
